ageas/__init__.py
ageas/main.py
ageas/classifier/__init__.py
ageas/classifier/cnn.py
ageas/classifier/svm.py
ageas/classifier/xgb.py
ageas/data/config/long_config.js
ageas/data/config/sample_config.js
ageas/data/config/simple_config.js
ageas/data/mouse/ENS2UniID.js.gz
ageas/data/mouse/GSName2UniID.js.gz
ageas/data/mouse/Tranfac201803_MotifTFsF.txt
ageas/data/mouse/wholeGene.js.gz
ageas/database_setup/__init__.py
ageas/database_setup/binary_class.py
ageas/lib/__init__.py
ageas/lib/deg_finder.py
ageas/lib/grp_predictor.py
ageas/lib/pcgrn_caster.py
ageas/operator/__init__.py
ageas/operator/feature_extractor.py
ageas/operator/gem_db_loader.py
ageas/operator/grn_guidance.py
ageas/operator/model_interpreter.py
ageas/operator/reporter.py
ageas/operator/trainer.py
ageas/tool/__init__.py
ageas/tool/atac_peaks.py
ageas/tool/biogrid.py
ageas/tool/gem.py
ageas/tool/grn.py
ageas/tool/grtd.py
ageas/tool/json.py
ageas/tool/transfac.py
ageas/tool/uniprot_id_map.py
Ageas-0.0.1a1.dist-info/LICENSE
Ageas-0.0.1a1.dist-info/METADATA
Ageas-0.0.1a1.dist-info/WHEEL
Ageas-0.0.1a1.dist-info/top_level.txt
Ageas-0.0.1a1.dist-info/RECORD
