Metadata-Version: 2.1
Name: Ageas
Version: 0.0.1a1
Summary: AutoML-based Genomic fEatrue extrAction System
Home-page: https://github.com/nkmtmsys/Ageas
Author: nkmtmsys
Author-email: gyu17@alumni.jh.edu
License: UNKNOWN
Project-URL: Bug Tracker, https://github.com/nkmtmsys/Ageas/issues
Platform: UNKNOWN
Classifier: Programming Language :: Python :: 3
Classifier: License :: OSI Approved :: MIT License
Classifier: Operating System :: OS Independent
Requires-Python: >=3.6
